{
    "title": "ICON Temperature 2m",
    "abstract": "Temperature 2m from ICON",
    "producer": "icon_surface",
    "views": [
        {
            "layers": [
                {
                    "qid": "l",
                    "layer_type": "isoband",
                    "parameter": "Temperature",
                    "isobands": "json:isobands/temperature.json",
                    "css": "isobands/temperature.css",
                    "attributes": {
                        "shape-rendering": "crispEdges"
                    }
                }
            ]
        }
    ]
}