{
    "title" : "Temperature",
    "abstract" : "Temperature 2m from MEPS",
    "projection": {},
    "producer": "meps_northeurope_surface",
    "views": [{
        "layers": [{
            "qid": "l",
            "layer_type": "isoband",
            "isobands": "json:/resources/isobands/temperature.json",
            "css": "/resources/isobands/temperature.css",
            "parameter": "Temperature",
            "attributes": {
                "shape-rendering": "crispEdges"
            }
        }]
    }]
}
